CNAsim/__init__.py
CNAsim/format_profiles.py
CNAsim/main.py
CNAsim/noise.py
CNAsim/reads.py
CNAsim/sequence.py
CNAsim/sim_genomes.py
CNAsim/tree.py
CNAsim/utilities.py
cnasim-1.3.5.dist-info/LICENSE
cnasim-1.3.5.dist-info/METADATA
cnasim-1.3.5.dist-info/WHEEL
cnasim-1.3.5.dist-info/entry_points.txt
cnasim-1.3.5.dist-info/top_level.txt
cnasim-1.3.5.dist-info/RECORD
