Metadata-Version: 2.2
Name: CNAsim
Version: 1.3.5
Summary: CNAsim is a software package for simulation of single-cell CNA data from tumors.
Home-page: https://github.com/samsonweiner/CNAsim
Author: Samson Weiner
Author-email: samson.weiner@uconn.edu
Classifier: Programming Language :: Python :: 3
Classifier: License :: OSI Approved :: MIT License
Classifier: Operating System :: OS Independent
Requires-Python: >=3.7
License-File: LICENSE
Dynamic: author
Dynamic: author-email
Dynamic: classifier
Dynamic: description
Dynamic: description-content-type
Dynamic: home-page
Dynamic: requires-python
Dynamic: summary
